PC_Azure/__init__.py
PC_Azure/_version.py
PC_Azure/az_key_vault.py
PC_Azure-1.0.1.post4.dist-info/LICENSE
PC_Azure-1.0.1.post4.dist-info/METADATA
PC_Azure-1.0.1.post4.dist-info/WHEEL
PC_Azure-1.0.1.post4.dist-info/top_level.txt
PC_Azure-1.0.1.post4.dist-info/RECORD
