Metadata-Version: 2.1
Name: PC_Azure
Version: 1.0.1.post4
Summary: This package includes modules to interact with Microsoft Azure.
Author-email: "Marcos E. Mercado" <marcos_elias@hotmail.com>
Keywords: Azure,Key Vault,secret,Microsoft
Classifier: Programming Language :: Python :: 3
Classifier: License :: OSI Approved :: MIT License
Classifier: Operating System :: OS Independent
Requires-Python: >=3.8
License-File: LICENSE
Requires-Dist: azure-identity
Requires-Dist: azure-keyvault-secrets
